usdm-0.66.0.dist-info/licenses/LICENSE
usdm_db/__init__.py
usdm_db/cross_reference.py
usdm_db/neo4j_dict.py
usdm_db/timeline.py
usdm_db/document/__init__.py
usdm_db/document/document.py
usdm_db/document/utility.py
usdm_db/errors_and_logging/__init__.py
usdm_db/errors_and_logging/error.py
usdm_db/errors_and_logging/errors.py
usdm_db/errors_and_logging/errors_and_logging.py
usdm_db/fhir/__init__.py
usdm_db/fhir/from_fhir.py
usdm_db/fhir/to_fhir.py
usdm_excel/__init__.py
usdm_excel/alias.py
usdm_excel/base_manager.py
usdm_excel/base_sheet.py
usdm_excel/cdisc_bc_library.py
usdm_excel/cdisc_ct.py
usdm_excel/cdisc_ct_library.py
usdm_excel/code_base.py
usdm_excel/configuration_sheet.py
usdm_excel/cross_ref.py
usdm_excel/ct_version_manager.py
usdm_excel/duplicate_object.py
usdm_excel/globals.py
usdm_excel/id_manager.py
usdm_excel/iso_3166.py
usdm_excel/iso_8601_duration.py
usdm_excel/ncit.py
usdm_excel/option_manager.py
usdm_excel/other_ct.py
usdm_excel/quantity_type.py
usdm_excel/range_type.py
usdm_excel/syntax_template_sheet.py
usdm_excel/template_manager.py
usdm_excel/abbreviation_sheet/__init__.py
usdm_excel/abbreviation_sheet/abbreviation_sheet.py
usdm_excel/annotation_sheet/__init__.py
usdm_excel/annotation_sheet/annotation_sheet.py
usdm_excel/assigned_person_sheet/__init__.py
usdm_excel/assigned_person_sheet/assigned_person_sheet.py
usdm_excel/data/cdisc_bcs.yaml
usdm_excel/data/cdisc_ct_2024-09-27.yaml
usdm_excel/data/cdisc_ct_2025-09-26.yaml
usdm_excel/data/cdisc_ct_config.yaml
usdm_excel/data/iso_3166.json
usdm_excel/data/missing_ct.yaml
usdm_excel/document/__init__.py
usdm_excel/document/elements.py
usdm_excel/document/macros.py
usdm_excel/document/soa.py
usdm_excel/document/template_base.py
usdm_excel/document/template_m11.py
usdm_excel/document/template_plain.py
usdm_excel/document/utility.py
usdm_excel/errors_and_logging/__init__.py
usdm_excel/errors_and_logging/error.py
usdm_excel/errors_and_logging/errors.py
usdm_excel/errors_and_logging/errors_and_logging.py
usdm-0.66.0.dist-info/METADATA
usdm-0.66.0.dist-info/WHEEL
usdm-0.66.0.dist-info/top_level.txt
usdm-0.66.0.dist-info/RECORD
