Metadata-Version: 2.4
Name: usdm
Version: 0.66.0
Summary: A python package for using the CDISC TransCelerate USDM
Author: D Iberson-Hurst
Author-email: 
Classifier: Intended Audience :: Developers
Classifier: Programming Language :: Python
Classifier: Programming Language :: Python :: 3
Classifier: Programming Language :: Python :: 3.10
Classifier: Operating System :: OS Independent
License-File: LICENSE
Requires-Dist: pandas
Requires-Dist: openpyxl
Requires-Dist: pydantic
Requires-Dist: requests
Requires-Dist: stringcase
Requires-Dist: yattag
Requires-Dist: docraptor
Requires-Dist: beautifulsoup4
Requires-Dist: pyyaml
Requires-Dist: fhir.resources
Dynamic: author
Dynamic: classifier
Dynamic: description
Dynamic: description-content-type
Dynamic: license-file
Dynamic: requires-dist
Dynamic: summary
